{
  "start_bn": 8596042,
  "end_bn": 8596162,
  "blocks": [
    {
      "bn": 8596043,
      "n_tx": 14267,
      "gas_used": 499918084,
      "gas_limit": 500000000,
      "fill_pct": 100.0,
      "timestamp": 1775596936
    },
    {
      "bn": 8596044,
      "n_tx": 14267,
      "gas_used": 499912496,
      "gas_limit": 500000000,
      "fill_pct": 100.0,
      "timestamp": 1775596937
    },
    {
      "bn": 8596045,
      "n_tx": 14267,
      "gas_used": 499918084,
      "gas_limit": 500000000,
      "fill_pct": 100.0,
      "timestamp": 1775596938
    },
    {
      "bn": 8596046,
      "n_tx": 14267,
      "gas_used": 499912496,
      "gas_limit": 500000000,
      "fill_pct": 100.0,
      "timestamp": 1775596939
    },
    {
      "bn": 8596047,
      "n_tx": 14267,
      "gas_used": 499918084,
      "gas_limit": 500000000,
      "fill_pct": 100.0,
      "timestamp": 1775596940
    },
    {
      "bn": 8596048,
      "n_tx": 14267,
      "gas_used": 499912496,
      "gas_limit": 500000000,
      "fill_pct": 100.0,
      "timestamp": 1775596941
    },
    {
      "bn": 8596049,
      "n_tx": 14267,
      "gas_used": 499918084,
      "gas_limit": 500000000,
      "fill_pct": 100.0,
      "timestamp": 1775596942
    },
    {
      "bn": 8596050,
      "n_tx": 8689,
      "gas_used": 304464954,
      "gas_limit": 500000000,
      "fill_pct": 60.9,
      "timestamp": 1775596943
    },
    {
      "bn": 8596051,
      "n_tx": 13341,
      "gas_used": 467471970,
      "gas_limit": 500000000,
      "fill_pct": 93.5,
      "timestamp": 1775596944
    },
    {
      "bn": 8596052,
      "n_tx": 14267,
      "gas_used": 499912496,
      "gas_limit": 500000000,
      "fill_pct": 100.0,
      "timestamp": 1775596945
    },
    {
      "bn": 8596053,
      "n_tx": 14267,
      "gas_used": 499918084,
      "gas_limit": 500000000,
      "fill_pct": 100.0,
      "timestamp": 1775596946
    },
    {
      "bn": 8596054,
      "n_tx": 13320,
      "gas_used": 466730563,
      "gas_limit": 500000000,
      "fill_pct": 93.3,
      "timestamp": 1775596947
    },
    {
      "bn": 8596055,
      "n_tx": 9041,
      "gas_used": 316804270,
      "gas_limit": 500000000,
      "fill_pct": 63.4,
      "timestamp": 1775596948
    },
    {
      "bn": 8596056,
      "n_tx": 8276,
      "gas_used": 289993847,
      "gas_limit": 500000000,
      "fill_pct": 58.0,
      "timestamp": 1775596949
    },
    {
      "bn": 8596057,
      "n_tx": 14248,
      "gas_used": 499252343,
      "gas_limit": 500000000,
      "fill_pct": 99.9,
      "timestamp": 1775596950
    },
    {
      "bn": 8596058,
      "n_tx": 14267,
      "gas_used": 499912496,
      "gas_limit": 500000000,
      "fill_pct": 100.0,
      "timestamp": 1775596951
    },
    {
      "bn": 8596059,
      "n_tx": 14267,
      "gas_used": 499912496,
      "gas_limit": 500000000,
      "fill_pct": 100.0,
      "timestamp": 1775596952
    },
    {
      "bn": 8596060,
      "n_tx": 14267,
      "gas_used": 499912496,
      "gas_limit": 500000000,
      "fill_pct": 100.0,
      "timestamp": 1775596953
    },
    {
      "bn": 8596061,
      "n_tx": 14267,
      "gas_used": 499918084,
      "gas_limit": 500000000,
      "fill_pct": 100.0,
      "timestamp": 1775596954
    },
    {
      "bn": 8596062,
      "n_tx": 14267,
      "gas_used": 499915284,
      "gas_limit": 500000000,
      "fill_pct": 100.0,
      "timestamp": 1775596955
    },
    {
      "bn": 8596063,
      "n_tx": 9193,
      "gas_used": 322124610,
      "gas_limit": 500000000,
      "fill_pct": 64.4,
      "timestamp": 1775596956
    },
    {
      "bn": 8596064,
      "n_tx": 8392,
      "gas_used": 294058371,
      "gas_limit": 500000000,
      "fill_pct": 58.8,
      "timestamp": 1775596957
    },
    {
      "bn": 8596065,
      "n_tx": 9745,
      "gas_used": 341471726,
      "gas_limit": 500000000,
      "fill_pct": 68.3,
      "timestamp": 1775596958
    },
    {
      "bn": 8596066,
      "n_tx": 14267,
      "gas_used": 499915284,
      "gas_limit": 500000000,
      "fill_pct": 100.0,
      "timestamp": 1775596959
    },
    {
      "bn": 8596067,
      "n_tx": 14267,
      "gas_used": 499915284,
      "gas_limit": 500000000,
      "fill_pct": 100.0,
      "timestamp": 1775596960
    },
    {
      "bn": 8596068,
      "n_tx": 14267,
      "gas_used": 499912496,
      "gas_limit": 500000000,
      "fill_pct": 100.0,
      "timestamp": 1775596961
    },
    {
      "bn": 8596069,
      "n_tx": 14267,
      "gas_used": 499918084,
      "gas_limit": 500000000,
      "fill_pct": 100.0,
      "timestamp": 1775596962
    },
    {
      "bn": 8596070,
      "n_tx": 14267,
      "gas_used": 499912496,
      "gas_limit": 500000000,
      "fill_pct": 100.0,
      "timestamp": 1775596963
    },
    {
      "bn": 8596071,
      "n_tx": 14267,
      "gas_used": 499918084,
      "gas_limit": 500000000,
      "fill_pct": 100.0,
      "timestamp": 1775596964
    },
    {
      "bn": 8596072,
      "n_tx": 13468,
      "gas_used": 471916335,
      "gas_limit": 500000000,
      "fill_pct": 94.4,
      "timestamp": 1775596965
    },
    {
      "bn": 8596073,
      "n_tx": 7715,
      "gas_used": 270342532,
      "gas_limit": 500000000,
      "fill_pct": 54.1,
      "timestamp": 1775596966
    },
    {
      "bn": 8596074,
      "n_tx": 11735,
      "gas_used": 411193724,
      "gas_limit": 500000000,
      "fill_pct": 82.2,
      "timestamp": 1775596967
    },
    {
      "bn": 8596075,
      "n_tx": 14267,
      "gas_used": 499918084,
      "gas_limit": 500000000,
      "fill_pct": 100.0,
      "timestamp": 1775596968
    },
    {
      "bn": 8596076,
      "n_tx": 14267,
      "gas_used": 499912496,
      "gas_limit": 500000000,
      "fill_pct": 100.0,
      "timestamp": 1775596969
    },
    {
      "bn": 8596077,
      "n_tx": 14267,
      "gas_used": 499918084,
      "gas_limit": 500000000,
      "fill_pct": 100.0,
      "timestamp": 1775596970
    },
    {
      "bn": 8596078,
      "n_tx": 9279,
      "gas_used": 325137964,
      "gas_limit": 500000000,
      "fill_pct": 65.0,
      "timestamp": 1775596971
    },
    {
      "bn": 8596079,
      "n_tx": 7378,
      "gas_used": 258534413,
      "gas_limit": 500000000,
      "fill_pct": 51.7,
      "timestamp": 1775596972
    },
    {
      "bn": 8596080,
      "n_tx": 8493,
      "gas_used": 297597310,
      "gas_limit": 500000000,
      "fill_pct": 59.5,
      "timestamp": 1775596973
    },
    {
      "bn": 8596081,
      "n_tx": 12565,
      "gas_used": 440281706,
      "gas_limit": 500000000,
      "fill_pct": 88.1,
      "timestamp": 1775596974
    },
    {
      "bn": 8596082,
      "n_tx": 14267,
      "gas_used": 499912496,
      "gas_limit": 500000000,
      "fill_pct": 100.0,
      "timestamp": 1775596975
    },
    {
      "bn": 8596083,
      "n_tx": 14267,
      "gas_used": 499912496,
      "gas_limit": 500000000,
      "fill_pct": 100.0,
      "timestamp": 1775596976
    },
    {
      "bn": 8596084,
      "n_tx": 14267,
      "gas_used": 499918084,
      "gas_limit": 500000000,
      "fill_pct": 100.0,
      "timestamp": 1775596977
    },
    {
      "bn": 8596085,
      "n_tx": 12434,
      "gas_used": 435686009,
      "gas_limit": 500000000,
      "fill_pct": 87.1,
      "timestamp": 1775596978
    },
    {
      "bn": 8596086,
      "n_tx": 13003,
      "gas_used": 455628788,
      "gas_limit": 500000000,
      "fill_pct": 91.1,
      "timestamp": 1775596979
    },
    {
      "bn": 8596087,
      "n_tx": 12808,
      "gas_used": 448790595,
      "gas_limit": 500000000,
      "fill_pct": 89.8,
      "timestamp": 1775596980
    },
    {
      "bn": 8596088,
      "n_tx": 8549,
      "gas_used": 299559494,
      "gas_limit": 500000000,
      "fill_pct": 59.9,
      "timestamp": 1775596981
    },
    {
      "bn": 8596089,
      "n_tx": 11557,
      "gas_used": 404962394,
      "gas_limit": 500000000,
      "fill_pct": 81.0,
      "timestamp": 1775596982
    },
    {
      "bn": 8596090,
      "n_tx": 14267,
      "gas_used": 499915272,
      "gas_limit": 500000000,
      "fill_pct": 100.0,
      "timestamp": 1775596983
    },
    {
      "bn": 8596091,
      "n_tx": 14267,
      "gas_used": 499915284,
      "gas_limit": 500000000,
      "fill_pct": 100.0,
      "timestamp": 1775596984
    },
    {
      "bn": 8596092,
      "n_tx": 14267,
      "gas_used": 499912496,
      "gas_limit": 500000000,
      "fill_pct": 100.0,
      "timestamp": 1775596985
    },
    {
      "bn": 8596093,
      "n_tx": 14267,
      "gas_used": 499918072,
      "gas_limit": 500000000,
      "fill_pct": 100.0,
      "timestamp": 1775596986
    },
    {
      "bn": 8596094,
      "n_tx": 8958,
      "gas_used": 313890433,
      "gas_limit": 500000000,
      "fill_pct": 62.8,
      "timestamp": 1775596987
    },
    {
      "bn": 8596095,
      "n_tx": 8153,
      "gas_used": 285689638,
      "gas_limit": 500000000,
      "fill_pct": 57.1,
      "timestamp": 1775596988
    },
    {
      "bn": 8596096,
      "n_tx": 9154,
      "gas_used": 320758089,
      "gas_limit": 500000000,
      "fill_pct": 64.2,
      "timestamp": 1775596989
    },
    {
      "bn": 8596097,
      "n_tx": 13500,
      "gas_used": 473043171,
      "gas_limit": 500000000,
      "fill_pct": 94.6,
      "timestamp": 1775596990
    },
    {
      "bn": 8596098,
      "n_tx": 12860,
      "gas_used": 450612623,
      "gas_limit": 500000000,
      "fill_pct": 90.1,
      "timestamp": 1775596991
    },
    {
      "bn": 8596099,
      "n_tx": 14267,
      "gas_used": 499918084,
      "gas_limit": 500000000,
      "fill_pct": 100.0,
      "timestamp": 1775596992
    },
    {
      "bn": 8596100,
      "n_tx": 14267,
      "gas_used": 499912496,
      "gas_limit": 500000000,
      "fill_pct": 100.0,
      "timestamp": 1775596993
    },
    {
      "bn": 8596101,
      "n_tx": 14267,
      "gas_used": 499918084,
      "gas_limit": 500000000,
      "fill_pct": 100.0,
      "timestamp": 1775596994
    },
    {
      "bn": 8596102,
      "n_tx": 14267,
      "gas_used": 499912496,
      "gas_limit": 500000000,
      "fill_pct": 100.0,
      "timestamp": 1775596995
    },
    {
      "bn": 8596103,
      "n_tx": 6689,
      "gas_used": 234392542,
      "gas_limit": 500000000,
      "fill_pct": 46.9,
      "timestamp": 1775596996
    },
    {
      "bn": 8596104,
      "n_tx": 3330,
      "gas_used": 116690953,
      "gas_limit": 500000000,
      "fill_pct": 23.3,
      "timestamp": 1775596997
    },
    {
      "bn": 8596105,
      "n_tx": 8537,
      "gas_used": 299144614,
      "gas_limit": 500000000,
      "fill_pct": 59.8,
      "timestamp": 1775596998
    },
    {
      "bn": 8596106,
      "n_tx": 14267,
      "gas_used": 499912496,
      "gas_limit": 500000000,
      "fill_pct": 100.0,
      "timestamp": 1775596999
    },
    {
      "bn": 8596107,
      "n_tx": 14267,
      "gas_used": 499912496,
      "gas_limit": 500000000,
      "fill_pct": 100.0,
      "timestamp": 1775597000
    },
    {
      "bn": 8596108,
      "n_tx": 8993,
      "gas_used": 315116810,
      "gas_limit": 500000000,
      "fill_pct": 63.0,
      "timestamp": 1775597001
    },
    {
      "bn": 8596109,
      "n_tx": 6266,
      "gas_used": 219571045,
      "gas_limit": 500000000,
      "fill_pct": 43.9,
      "timestamp": 1775597002
    },
    {
      "bn": 8596110,
      "n_tx": 8249,
      "gas_used": 289047794,
      "gas_limit": 500000000,
      "fill_pct": 57.8,
      "timestamp": 1775597003
    },
    {
      "bn": 8596111,
      "n_tx": 11479,
      "gas_used": 402229352,
      "gas_limit": 500000000,
      "fill_pct": 80.4,
      "timestamp": 1775597004
    },
    {
      "bn": 8596112,
      "n_tx": 14267,
      "gas_used": 499915272,
      "gas_limit": 500000000,
      "fill_pct": 100.0,
      "timestamp": 1775597005
    },
    {
      "bn": 8596113,
      "n_tx": 14267,
      "gas_used": 499915272,
      "gas_limit": 500000000,
      "fill_pct": 100.0,
      "timestamp": 1775597006
    },
    {
      "bn": 8596114,
      "n_tx": 14267,
      "gas_used": 499912484,
      "gas_limit": 500000000,
      "fill_pct": 100.0,
      "timestamp": 1775597007
    },
    {
      "bn": 8596115,
      "n_tx": 5882,
      "gas_used": 206116069,
      "gas_limit": 500000000,
      "fill_pct": 41.2,
      "timestamp": 1775597008
    },
    {
      "bn": 8596116,
      "n_tx": 6486,
      "gas_used": 227274037,
      "gas_limit": 500000000,
      "fill_pct": 45.5,
      "timestamp": 1775597009
    },
    {
      "bn": 8596117,
      "n_tx": 14267,
      "gas_used": 499918084,
      "gas_limit": 500000000,
      "fill_pct": 100.0,
      "timestamp": 1775597010
    },
    {
      "bn": 8596118,
      "n_tx": 9382,
      "gas_used": 328746981,
      "gas_limit": 500000000,
      "fill_pct": 65.7,
      "timestamp": 1775597011
    },
    {
      "bn": 8596119,
      "n_tx": 8262,
      "gas_used": 289508889,
      "gas_limit": 500000000,
      "fill_pct": 57.9,
      "timestamp": 1775597012
    },
    {
      "bn": 8596120,
      "n_tx": 10548,
      "gas_used": 369602455,
      "gas_limit": 500000000,
      "fill_pct": 73.9,
      "timestamp": 1775597013
    },
    {
      "bn": 8596121,
      "n_tx": 14267,
      "gas_used": 499918084,
      "gas_limit": 500000000,
      "fill_pct": 100.0,
      "timestamp": 1775597014
    },
    {
      "bn": 8596122,
      "n_tx": 14267,
      "gas_used": 499912496,
      "gas_limit": 500000000,
      "fill_pct": 100.0,
      "timestamp": 1775597015
    },
    {
      "bn": 8596123,
      "n_tx": 7577,
      "gas_used": 265507174,
      "gas_limit": 500000000,
      "fill_pct": 53.1,
      "timestamp": 1775597016
    },
    {
      "bn": 8596124,
      "n_tx": 7965,
      "gas_used": 279096718,
      "gas_limit": 500000000,
      "fill_pct": 55.8,
      "timestamp": 1775597017
    },
    {
      "bn": 8596125,
      "n_tx": 13621,
      "gas_used": 477282890,
      "gas_limit": 500000000,
      "fill_pct": 95.5,
      "timestamp": 1775597018
    },
    {
      "bn": 8596126,
      "n_tx": 13921,
      "gas_used": 487789002,
      "gas_limit": 500000000,
      "fill_pct": 97.6,
      "timestamp": 1775597019
    },
    {
      "bn": 8596127,
      "n_tx": 9452,
      "gas_used": 331205299,
      "gas_limit": 500000000,
      "fill_pct": 66.2,
      "timestamp": 1775597020
    },
    {
      "bn": 8596128,
      "n_tx": 14267,
      "gas_used": 499912496,
      "gas_limit": 500000000,
      "fill_pct": 100.0,
      "timestamp": 1775597021
    },
    {
      "bn": 8596129,
      "n_tx": 14267,
      "gas_used": 499918084,
      "gas_limit": 500000000,
      "fill_pct": 100.0,
      "timestamp": 1775597022
    },
    {
      "bn": 8596130,
      "n_tx": 14267,
      "gas_used": 499912496,
      "gas_limit": 500000000,
      "fill_pct": 100.0,
      "timestamp": 1775597023
    },
    {
      "bn": 8596131,
      "n_tx": 14267,
      "gas_used": 499912496,
      "gas_limit": 500000000,
      "fill_pct": 100.0,
      "timestamp": 1775597024
    },
    {
      "bn": 8596132,
      "n_tx": 14267,
      "gas_used": 499918072,
      "gas_limit": 500000000,
      "fill_pct": 100.0,
      "timestamp": 1775597025
    },
    {
      "bn": 8596133,
      "n_tx": 14267,
      "gas_used": 499912484,
      "gas_limit": 500000000,
      "fill_pct": 100.0,
      "timestamp": 1775597026
    },
    {
      "bn": 8596134,
      "n_tx": 12644,
      "gas_used": 443044187,
      "gas_limit": 500000000,
      "fill_pct": 88.6,
      "timestamp": 1775597027
    },
    {
      "bn": 8596135,
      "n_tx": 8787,
      "gas_used": 307904364,
      "gas_limit": 500000000,
      "fill_pct": 61.6,
      "timestamp": 1775597028
    },
    {
      "bn": 8596136,
      "n_tx": 11279,
      "gas_used": 395215964,
      "gas_limit": 500000000,
      "fill_pct": 79.0,
      "timestamp": 1775597029
    },
    {
      "bn": 8596137,
      "n_tx": 8050,
      "gas_used": 282080621,
      "gas_limit": 500000000,
      "fill_pct": 56.4,
      "timestamp": 1775597030
    },
    {
      "bn": 8596138,
      "n_tx": 10144,
      "gas_used": 355449487,
      "gas_limit": 500000000,
      "fill_pct": 71.1,
      "timestamp": 1775597031
    },
    {
      "bn": 8596139,
      "n_tx": 5946,
      "gas_used": 208355765,
      "gas_limit": 500000000,
      "fill_pct": 41.7,
      "timestamp": 1775597032
    },
    {
      "bn": 8596140,
      "n_tx": 11081,
      "gas_used": 388278242,
      "gas_limit": 500000000,
      "fill_pct": 77.7,
      "timestamp": 1775597033
    },
    {
      "bn": 8596141,
      "n_tx": 14267,
      "gas_used": 499918084,
      "gas_limit": 500000000,
      "fill_pct": 100.0,
      "timestamp": 1775597034
    },
    {
      "bn": 8596142,
      "n_tx": 14267,
      "gas_used": 499912496,
      "gas_limit": 500000000,
      "fill_pct": 100.0,
      "timestamp": 1775597035
    },
    {
      "bn": 8596143,
      "n_tx": 13428,
      "gas_used": 470520363,
      "gas_limit": 500000000,
      "fill_pct": 94.1,
      "timestamp": 1775597036
    },
    {
      "bn": 8596144,
      "n_tx": 14267,
      "gas_used": 499912496,
      "gas_limit": 500000000,
      "fill_pct": 100.0,
      "timestamp": 1775597037
    },
    {
      "bn": 8596145,
      "n_tx": 14267,
      "gas_used": 499918084,
      "gas_limit": 500000000,
      "fill_pct": 100.0,
      "timestamp": 1775597038
    },
    {
      "bn": 8596146,
      "n_tx": 14267,
      "gas_used": 499912496,
      "gas_limit": 500000000,
      "fill_pct": 100.0,
      "timestamp": 1775597039
    },
    {
      "bn": 8596147,
      "n_tx": 14267,
      "gas_used": 499918072,
      "gas_limit": 500000000,
      "fill_pct": 100.0,
      "timestamp": 1775597040
    },
    {
      "bn": 8596148,
      "n_tx": 11462,
      "gas_used": 401628089,
      "gas_limit": 500000000,
      "fill_pct": 80.3,
      "timestamp": 1775597041
    },
    {
      "bn": 8596149,
      "n_tx": 6921,
      "gas_used": 242521590,
      "gas_limit": 500000000,
      "fill_pct": 48.5,
      "timestamp": 1775597042
    },
    {
      "bn": 8596150,
      "n_tx": 14267,
      "gas_used": 499912496,
      "gas_limit": 500000000,
      "fill_pct": 100.0,
      "timestamp": 1775597043
    },
    {
      "bn": 8596151,
      "n_tx": 7023,
      "gas_used": 246095568,
      "gas_limit": 500000000,
      "fill_pct": 49.2,
      "timestamp": 1775597044
    },
    {
      "bn": 8596152,
      "n_tx": 8549,
      "gas_used": 299559494,
      "gas_limit": 500000000,
      "fill_pct": 59.9,
      "timestamp": 1775597045
    },
    {
      "bn": 8596153,
      "n_tx": 10172,
      "gas_used": 356433379,
      "gas_limit": 500000000,
      "fill_pct": 71.3,
      "timestamp": 1775597046
    },
    {
      "bn": 8596154,
      "n_tx": 9376,
      "gas_used": 328536747,
      "gas_limit": 500000000,
      "fill_pct": 65.7,
      "timestamp": 1775597047
    },
    {
      "bn": 8596155,
      "n_tx": 8808,
      "gas_used": 308634595,
      "gas_limit": 500000000,
      "fill_pct": 61.7,
      "timestamp": 1775597048
    },
    {
      "bn": 8596156,
      "n_tx": 13424,
      "gas_used": 470374619,
      "gas_limit": 500000000,
      "fill_pct": 94.1,
      "timestamp": 1775597049
    },
    {
      "bn": 8596157,
      "n_tx": 14267,
      "gas_used": 499918084,
      "gas_limit": 500000000,
      "fill_pct": 100.0,
      "timestamp": 1775597050
    },
    {
      "bn": 8596158,
      "n_tx": 10994,
      "gas_used": 385229849,
      "gas_limit": 500000000,
      "fill_pct": 77.0,
      "timestamp": 1775597051
    },
    {
      "bn": 8596159,
      "n_tx": 14267,
      "gas_used": 499918084,
      "gas_limit": 500000000,
      "fill_pct": 100.0,
      "timestamp": 1775597052
    },
    {
      "bn": 8596160,
      "n_tx": 14267,
      "gas_used": 499915284,
      "gas_limit": 500000000,
      "fill_pct": 100.0,
      "timestamp": 1775597053
    },
    {
      "bn": 8596161,
      "n_tx": 14267,
      "gas_used": 499915284,
      "gas_limit": 500000000,
      "fill_pct": 100.0,
      "timestamp": 1775597054
    },
    {
      "bn": 8596162,
      "n_tx": 14267,
      "gas_used": 499912496,
      "gas_limit": 500000000,
      "fill_pct": 100.0,
      "timestamp": 1775597055
    }
  ]
}